flask_state/__about__.py
flask_state/__init__.py
flask_state/conf/__init__.py
flask_state/conf/config.py
flask_state/controller/__init__.py
flask_state/controller/manager.py
flask_state/controller/response_methods.py
flask_state/dao/__init__.py
flask_state/dao/host_status.py
flask_state/exceptions/__init__.py
flask_state/exceptions/error_code.py
flask_state/exceptions/log_msg.py
flask_state/models/__init__.py
flask_state/models/flask_state_host.py
flask_state/services/__init__.py
flask_state/services/host_status.py
flask_state/utils/__init__.py
flask_state/utils/auth.py
flask_state/utils/date.py
flask_state/utils/file_lock.py
flask_state/utils/format_conf.py
flask_state/utils/logger.py
Flask_State_test-1.0.2b1.dist-info/METADATA
Flask_State_test-1.0.2b1.dist-info/WHEEL
Flask_State_test-1.0.2b1.dist-info/top_level.txt
Flask_State_test-1.0.2b1.dist-info/RECORD
